llmdev/__about__.py
llmdev/__init__.py
llmdev/llogger.py
llmdev/version.txt
llmdev-1.0.0.dist-info/LICENSE
llmdev-1.0.0.dist-info/METADATA
llmdev-1.0.0.dist-info/WHEEL
llmdev-1.0.0.dist-info/RECORD
