Metadata-Version: 2.1
Name: llmdev
Version: 1.0.0
Summary: Tools for LLM applications development
Home-page: https://github.com/incubeai/llmdev
License: MIT
Author: Incubeai
Author-email: incubeai.tech@gmail.com
Requires-Python: >=3.11,<4.0
Classifier: License :: OSI Approved :: MIT License
Classifier: Programming Language :: Python :: 3
Classifier: Programming Language :: Python :: 3.11
Classifier: Programming Language :: Python :: 3.12
